LICENSE
README.md
setup.cfg
setup.py
neural_tree/__init__.py
neural_tree/__version__.py
neural_tree.egg-info/PKG-INFO
neural_tree.egg-info/SOURCES.txt
neural_tree.egg-info/dependency_links.txt
neural_tree.egg-info/requires.txt
neural_tree.egg-info/top_level.txt
neural_tree/clustering/__init__.py
neural_tree/clustering/average.py
neural_tree/clustering/kmeans.py
neural_tree/clustering/optimize.py
neural_tree/datasets/__init__.py
neural_tree/datasets/beir.py
neural_tree/leafs/__init__.py
neural_tree/leafs/leaf.py
neural_tree/nodes/__init__.py
neural_tree/nodes/node.py
neural_tree/retrievers/__init__.py
neural_tree/retrievers/colbert.py
neural_tree/retrievers/sentence_transformer.py
neural_tree/retrievers/tfidf.py
neural_tree/scoring/__init__.py
neural_tree/scoring/base.py
neural_tree/scoring/colbert.py
neural_tree/scoring/sentence_transformer.py
neural_tree/scoring/tfidf.py
neural_tree/trees/__init__.py
neural_tree/trees/colbert.py
neural_tree/trees/sentence_transformer.py
neural_tree/trees/tfidf.py
neural_tree/trees/tree.py
neural_tree/utils/__init__.py
neural_tree/utils/batchify.py
neural_tree/utils/evaluate.py
neural_tree/utils/iter.py
neural_tree/utils/sanity_check.py
neural_tree/utils/set_env.py