Metadata-Version: 2.1
Name: neural-tree
Version: 0.0.1
Summary: Neural-Tree
Home-page: https://github.com/raphaelsty/neural-tree
Download-URL: https://github.com/user/neural-tree/archive/v_01.tar.gz
Author: Raphael Sourty
Author-email: raphael.sourty@gmail.com
License: MIT
Keywords: tree search,neural search,information retrieval,semantic search,colbert,tree
Classifier: Programming Language :: Python :: 3
Classifier: License :: OSI Approved :: MIT License
Classifier: Operating System :: OS Independent
Requires-Python: >=3.6
Provides-Extra: eval
Provides-Extra: dev
License-File: LICENSE
